pyswizzle/__init__.py
pyswizzle/pyswizzle.py
pyswizzle-1.0.2.dist-info/METADATA
pyswizzle-1.0.2.dist-info/WHEEL
pyswizzle-1.0.2.dist-info/licenses/LICENSE
pyswizzle-1.0.2.dist-info/RECORD
