Metadata-Version: 2.3
Name: pyswizzle
Version: 1.0.2
Summary: Python implementation of swizzle and deswizzle of video games textures
Project-URL: Homepage, https://github.com/Aclios/pyswizzle
Project-URL: Issues, https://github.com/Aclios/pyswizzle/issues
Author: Aclios
License-File: LICENSE
Classifier: License :: OSI Approved :: MIT License
Classifier: Operating System :: OS Independent
Classifier: Programming Language :: Python :: 3
Requires-Python: >=3.0
Requires-Dist: numpy
